MANIFEST.in
setup.cfg
setup.py
stabilizer_search/__init__.py
stabilizer_search.egg-info/PKG-INFO
stabilizer_search.egg-info/SOURCES.txt
stabilizer_search.egg-info/dependency_links.txt
stabilizer_search.egg-info/requires.txt
stabilizer_search.egg-info/top_level.txt
stabilizer_search/linalg/__init__.py
stabilizer_search/linalg/cy_gram_schmidt.c
stabilizer_search/linalg/cy_gram_schmidt.pyx
stabilizer_search/linalg/gram_schmidt.py
stabilizer_search/mat/Makefile
stabilizer_search/mat/__init__.py
stabilizer_search/mat/haar_random.c
stabilizer_search/mat/haar_random.pyx
stabilizer_search/mat/haarrandom.c
stabilizer_search/mat/haarrandom.h
stabilizer_search/mat/py_haar_random.py
stabilizer_search/mat/__pycache__/haar_random.pyx
stabilizer_search/search/__init__.py
stabilizer_search/search/_result.py
stabilizer_search/search/_search.py
stabilizer_search/search/brute_force.py
stabilizer_search/search/cy_do_random_walk.c
stabilizer_search/search/cy_do_random_walk.pyx
stabilizer_search/search/random_walk.py
stabilizer_search/stabilizers/__init__.py
stabilizer_search/stabilizers/cy_eigenstates.c
stabilizer_search/stabilizers/cy_eigenstates.pyx
stabilizer_search/stabilizers/eigenstates.py
stabilizer_search/stabilizers/py_generators.py
stabilizer_search/stabilizers/utils.py