Metadata-Version: 1.0
Name: stabilizer-search
Version: 1.1.0
Summary: Stabilizer Search
Home-page: https://github.com/padraic-padraic/StabilizerSearch
Author: Padraic Calpin
Author-email: UNKNOWN
License: GPLv3.0
Keywords: quantum computing stabilizers simulation
Platform: UNKNOWN
